<?xml version="1.0" encoding="utf-8" ?><dwsync><file name="birds.mp4" server="ftp.differentsignal.com/public_html/" local="3516115002" remote="318763443909116763" Dst="-1" /><file name="birds.webm" server="ftp.differentsignal.com/public_html/" local="3516124364" remote="318763443909116841" Dst="-1" /><file name="bubble.mp4" server="ftp.differentsignal.com/public_html/" local="3516169875" remote="318763443909118305" Dst="-1" /><file name="bubble.webm" server="ftp.differentsignal.com/public_html/" local="3516174740" remote="318763443909118360" Dst="-1" /><file name="rain.mp4" server="ftp.differentsignal.com/public_html/" local="3516119232" remote="318763443909120342" Dst="-1" /><file name="rain.webm" server="ftp.differentsignal.com/public_html/" local="3516119796" remote="318763443909120427" Dst="-1" /><file name="surf.mp4" server="ftp.differentsignal.com/public_html/" local="3516123411" remote="318763443909122564" Dst="-1" /><file name="surf.webm" server="ftp.differentsignal.com/public_html/" local="3516124571" remote="318763443909122663" Dst="-1" /><file name="water.mp4" server="ftp.differentsignal.com/public_html/" local="3516118833" remote="318763443909123675" Dst="-1" /><file name="birds.m4v" server="ftp.differentsignal.com/public_html/" local="3517839759" remote="318763443910737367" Dst="-1" /><file name="bubble.m4v" server="ftp.differentsignal.com/public_html/" local="3517839599" remote="318763443910737744" Dst="-1" /><file name="rain.m4v" server="ftp.differentsignal.com/public_html/" local="3517832169" remote="318763443910738326" Dst="-1" /><file name="surf.m4v" server="ftp.differentsignal.com/public_html/" local="3517839295" remote="318763443910739187" Dst="-1" /><file name=".htaccess" server="ftp.differentsignal.com/public_html/" local="3517841858" remote="318763443910739234" Dst="-1" /></dwsync>